webbpsf/__init__.py
webbpsf/constants.py
webbpsf/detectors.py
webbpsf/distortion.py
webbpsf/gridded_library.py
webbpsf/mast_wss.py
webbpsf/match_data.py
webbpsf/notes_new.txt
webbpsf/opds.py
webbpsf/optical_budget.py
webbpsf/optics.py
webbpsf/roman.py
webbpsf/surs.py
webbpsf/trending.py
webbpsf/utils.py
webbpsf/version.py
webbpsf/webbpsf_core.py
webbpsf/otelm/JWST_influence_functions_control_with_sm.fits
webbpsf/otelm/NIRCam_WL_Empirical_Power.csv
webbpsf/otelm/README.txt
webbpsf/otelm/SMIF_hexike.csv
webbpsf/otelm/__init__.py
webbpsf/otelm/coarse_track1_sim_pointing.fits
webbpsf/otelm/coarse_track2_sim_pointing.fits
webbpsf/otelm/jwst_wfe_summary_from_optical_budget.csv
webbpsf/otelm/seg_sens.txt
webbpsf/otelm/thermal_OPD_fitting_parameters_9H_um.fits
webbpsf/tests/README.txt
webbpsf/tests/__init__.py
webbpsf/tests/test_detectors.py
webbpsf/tests/test_distortion.py
webbpsf/tests/test_errorhandling.py
webbpsf/tests/test_fgs.py
webbpsf/tests/test_jitter.py
webbpsf/tests/test_mast_wss.py
webbpsf/tests/test_miri.py
webbpsf/tests/test_nircam.py
webbpsf/tests/test_niriss.py
webbpsf/tests/test_nirspec.py
webbpsf/tests/test_opds.py
webbpsf/tests/test_optical_budget.py
webbpsf/tests/test_psfgrid.py
webbpsf/tests/test_roman.py
webbpsf/tests/test_trending.py
webbpsf/tests/test_utils.py
webbpsf/tests/test_webbpsf.py
webbpsf/tests/test_webbpsf_stpsf_alias.py
webbpsf/tests/surs/__init__.py
webbpsf/tests/surs/example_alldof_A1-SM_sur.xml
webbpsf/tests/surs/example_coarse_phasing_N2019041204_sur.xml
webbpsf/tests/surs/example_fine_phasing_R201902010S_sur.xml
webbpsf/tests/surs/example_global_alignment_N201902010F_sur.xml
webbpsf/tests/surs/example_image_stacking_O201904110E_sur.xml
webbpsf-2.0.0.dist-info/LICENSE.md
webbpsf-2.0.0.dist-info/METADATA
webbpsf-2.0.0.dist-info/WHEEL
webbpsf-2.0.0.dist-info/top_level.txt
webbpsf-2.0.0.dist-info/RECORD
