Metadata-Version: 2.2
Name: webbpsf
Version: 2.0.0
Summary: Creates simulated point spread functions for the James Webb Space Telescope
Author-email: Association of Universities for Research in Astronomy <help@stsci.edu>
License: BSD 3-Clause License
Project-URL: Homepage, http://webbpsf.readthedocs.io/
Project-URL: github_project, https://github.com/spacetelescope/webbpsf
Requires-Python: >=3.10
License-File: LICENSE.md
Requires-Dist: stpsf>=1.5.2
Provides-Extra: test
Requires-Dist: pytest; extra == "test"
Requires-Dist: pytest-astropy; extra == "test"
Provides-Extra: docs
Requires-Dist: nbsphinx; extra == "docs"
Requires-Dist: sphinx; extra == "docs"
Requires-Dist: stsci_rtd_theme; extra == "docs"
Requires-Dist: sphinx-astropy; extra == "docs"
Requires-Dist: sphinx-automodapi; extra == "docs"
Requires-Dist: sphinx-issues; extra == "docs"
Requires-Dist: tomli; python_version < "3.11" and extra == "docs"
